rus_guard_integration/__init__.py
rus_guard_integration/core/__init__.py
rus_guard_integration/core/base_core.py
rus_guard_integration/core/rus_guard_core.py
rus_guard_integration/dto/__init__.py
rus_guard_integration/dto/acs_methods.py
rus_guard_integration/dto/config.py
rus_guard_integration/dto/model_dto.py
rus_guard_integration/dto/response_dto/__init__.py
rus_guard_integration/dto/response_dto/dto.py
rus_guard_integration-0.1.0.dist-info/LICENSE
rus_guard_integration-0.1.0.dist-info/METADATA
rus_guard_integration-0.1.0.dist-info/WHEEL
rus_guard_integration-0.1.0.dist-info/RECORD
