Metadata-Version: 2.1
Name: rus_guard_integration
Version: 0.1.0
Summary: Модуль интеграции со СКУД РусГард
Author: Mrkorogod
Requires-Python: >=3.10,<4.0
Classifier: Programming Language :: Python :: 3
Classifier: Programming Language :: Python :: 3.10
Classifier: Programming Language :: Python :: 3.11
Classifier: Programming Language :: Python :: 3.12
